antsibull_docs_parser/__init__.py
antsibull_docs_parser/_parser_impl.py
antsibull_docs_parser/ansible_doc_text.py
antsibull_docs_parser/dom.py
antsibull_docs_parser/format.py
antsibull_docs_parser/html.py
antsibull_docs_parser/md.py
antsibull_docs_parser/parser.py
antsibull_docs_parser/py.typed
antsibull_docs_parser/rst.py
antsibull_docs_parser-1.2.2.dist-info/METADATA
antsibull_docs_parser-1.2.2.dist-info/WHEEL
antsibull_docs_parser-1.2.2.dist-info/licenses/LICENSES/BSD-2-Clause.txt
antsibull_docs_parser-1.2.2.dist-info/licenses/LICENSES/GPL-3.0-or-later.txt
antsibull_docs_parser-1.2.2.dist-info/RECORD
