Metadata-Version: 2.4
Name: antsibull-docs-parser
Version: 1.2.2
Summary: Python library for processing Ansible documentation markup
Project-URL: Source code, https://github.com/ansible-community/antsibull-docs-parser/
Project-URL: Code of Conduct, https://docs.ansible.com/ansible/latest/community/code_of_conduct.html
Project-URL: Bug tracker, https://github.com/ansible-community/antsibull-docs-parser/issues
Project-URL: Changelog, https://github.com/ansible-community/antsibull-docs-parser/tree/main/CHANGELOG.md
Author-email: Felix Fontein <felix@fontein.de>
Maintainer-email: Felix Fontein <felix@fontein.de>, Maxwell G <maxwell@gtmx.me>
License-Expression: GPL-3.0-or-later AND BSD-2-Clause
License-File: LICENSES/BSD-2-Clause.txt
License-File: LICENSES/GPL-3.0-or-later.txt
Classifier: Development Status :: 5 - Production/Stable
Classifier: Framework :: Ansible
Classifier: Intended Audience :: Developers
Classifier: Programming Language :: Python :: 3
Classifier: Programming Language :: Python :: 3.9
Classifier: Programming Language :: Python :: 3.10
Classifier: Programming Language :: Python :: 3.11
Classifier: Programming Language :: Python :: 3.12
Classifier: Programming Language :: Python :: 3.13
Classifier: Typing :: Typed
Requires-Python: >=3.9
Provides-Extra: codeqa
Requires-Dist: antsibull-changelog; extra == 'codeqa'
Requires-Dist: flake8; extra == 'codeqa'
Requires-Dist: pylint; extra == 'codeqa'
Requires-Dist: reuse; extra == 'codeqa'
Provides-Extra: coverage
Requires-Dist: coverage[toml]; extra == 'coverage'
Provides-Extra: dev
Requires-Dist: antsibull-changelog; extra == 'dev'
Requires-Dist: black; extra == 'dev'
Requires-Dist: click<8.2.0; extra == 'dev'
Requires-Dist: coverage[toml]; extra == 'dev'
Requires-Dist: flake8; extra == 'dev'
Requires-Dist: isort; extra == 'dev'
Requires-Dist: mypy; extra == 'dev'
Requires-Dist: nox; extra == 'dev'
Requires-Dist: pylint; extra == 'dev'
Requires-Dist: pyre-check>=0.9.17; extra == 'dev'
Requires-Dist: pytest; extra == 'dev'
Requires-Dist: pytest-cov; extra == 'dev'
Requires-Dist: pytest-error-for-skips; extra == 'dev'
Requires-Dist: pyyaml; extra == 'dev'
Requires-Dist: reuse; extra == 'dev'
Provides-Extra: formatters
Requires-Dist: black; extra == 'formatters'
Requires-Dist: isort; extra == 'formatters'
Provides-Extra: test
Requires-Dist: pytest; extra == 'test'
Requires-Dist: pytest-cov; extra == 'test'
Requires-Dist: pytest-error-for-skips; extra == 'test'
Requires-Dist: pyyaml; extra == 'test'
Provides-Extra: typing
Requires-Dist: click<8.2.0; extra == 'typing'
Requires-Dist: mypy; extra == 'typing'
Requires-Dist: pyre-check>=0.9.17; extra == 'typing'
